odespy/__init__.py
odespy/condition_checks_v1.py
odespy/condition_checks_v2.py
odespy/estimation.py
odespy/initialization.py
odespy/norms.py
odespy/odespy.py
odespy/predictor_corrector.py
odespy/step_size.py
odespy/tableaux.py
odespy/test.py
odespy/test_functions.py
odespy-0.1.1.dist-info/LICENSE.txt
odespy-0.1.1.dist-info/METADATA
odespy-0.1.1.dist-info/WHEEL
odespy-0.1.1.dist-info/top_level.txt
odespy-0.1.1.dist-info/RECORD
