Metadata-Version: 2.1
Name: odespy
Version: 0.1.1
Summary: A library for solving various types of ordinary differential equations (ODEs)
Author-email: Vivi Andasari <vandasari@gmail.com>
Project-URL: Homepage, https://github.com/vandasari/odespy
Project-URL: Repository, https://github.com/vandasari/odespy
Project-URL: Issues, https://github.com/vandasari/odespy/issues
Keywords: ode,ordinary differential equation,ordinary differential equation,Runge-Kutta,predictor corrector,explicit solvers,non-stiff equations
Classifier: Programming Language :: Python :: 3
Classifier: License :: OSI Approved :: MIT License
Classifier: Operating System :: OS Independent
Requires-Python: >=3.9
License-File: LICENSE.txt
Requires-Dist: numpy >=1.25
